README.md
setup.py
optopy.egg-info/PKG-INFO
optopy.egg-info/SOURCES.txt
optopy.egg-info/dependency_links.txt
optopy.egg-info/requires.txt
optopy.egg-info/top_level.txt
optpy/__init__.py
optpy/costs.py
optpy/distributed_solvers.py
optpy/networks.py
optpy/prediction.py
optpy/sets.py
optpy/solvers.py
optpy/utils.py