Metadata-Version: 2.1
Name: optopy
Version: 0.1.0
Summary: optopy
Home-page: https://github.com/nicola-bastianello/optopy
Author: Nicola Bastianello
Author-email: nicola.bastianello.3@phd.unipd.it
License: UNKNOWN
Platform: UNKNOWN
Classifier: Programming Language :: Python :: 3
Classifier: License :: OSI Approved :: GNU General Public License v3 (GPLv3)
Classifier: Operating System :: OS Independent
Requires-Python: >=3.7
